MANIFEST.in
README.rst
setup.py
sparkprob/__init__.py
sparkprob/sparkprob.py
sparkprob.egg-info/PKG-INFO
sparkprob.egg-info/SOURCES.txt
sparkprob.egg-info/dependency_links.txt
sparkprob.egg-info/not-zip-safe
sparkprob.egg-info/top_level.txt