Metadata-Version: 1.1
Name: sparkprob
Version: 0.1
Summary: Sparklines for probability distributions
Home-page: https://github.com/ccorcos/sparkprob
Author: Chet Corcos
Author-email: ccorcos@gmail
License: MIT
Keywords: sparklines probability distribution print bar graph
Platform: UNKNOWN
Classifier: Development Status :: 2 - Pre-Alpha
Classifier: Programming Language :: Python :: 2.7
Classifier: Intended Audience :: Science/Research
